tool_for_enabled_by/__init__.py
tool_for_enabled_by/tools/__init__.py
tool_for_enabled_by/tools/tool_with_enabled_by_value_enum.py
tool_for_enabled_by/tools/utils.py
tool_for_enabled_by-0.0.4.dist-info/METADATA
tool_for_enabled_by-0.0.4.dist-info/WHEEL
tool_for_enabled_by-0.0.4.dist-info/entry_points.txt
tool_for_enabled_by-0.0.4.dist-info/top_level.txt
tool_for_enabled_by-0.0.4.dist-info/RECORD
