Metadata-Version: 2.1
Name: tool-for-enabled-by
Version: 0.0.4
Summary: This is a tool to test enabled_by
